dizi/__init__.py
dizi/constants.py
dizi/core.py
dizi-1.1.dist-info/METADATA
dizi-1.1.dist-info/WHEEL
dizi-1.1.dist-info/top_level.txt
dizi-1.1.dist-info/RECORD
