Metadata-Version: 2.4
Name: dizi
Version: 1.1
Summary: Dizi theme
Author: Dang Dizi
Author-email: dangdizi.75@gmail.com
Requires-Python: >=3.7
Dynamic: author
Dynamic: author-email
Dynamic: description-content-type
Dynamic: requires-python
Dynamic: summary
